srlife/__init__.py
srlife/damage.py
srlife/helpers.py
srlife/library.py
srlife/managers.py
srlife/materials.py
srlife/receiver.py
srlife/solverparams.py
srlife/solvers.py
srlife/spring.py
srlife/structural.py
srlife/system.py
srlife/thermal.py
srlife/writers.py
srlife/data/damage/316H.xml
srlife/data/damage/740H.xml
srlife/data/damage/800H.xml
srlife/data/damage/A230.xml
srlife/data/damage/A282.xml
srlife/data/damage/A617.xml
srlife/data/damage/SiC.xml
srlife/data/deformation/316H.xml
srlife/data/deformation/740H.xml
srlife/data/deformation/800H.xml
srlife/data/deformation/A230.xml
srlife/data/deformation/A282.xml
srlife/data/deformation/A617.xml
srlife/data/deformation/SiC.xml
srlife/data/fluid/salt.xml
srlife/data/fluid/salt_SiC.xml
srlife/data/thermal/316H.xml
srlife/data/thermal/740H.xml
srlife/data/thermal/800H.xml
srlife/data/thermal/A230.xml
srlife/data/thermal/A282.xml
srlife/data/thermal/A617.xml
srlife/data/thermal/SiC.xml
srlife/data/thermalfluid/32MgCl2-68KCl.xml
srlife/data/thermalfluid/sCO2.xml
srlife/thermohydraulics/__init__.py
srlife/thermohydraulics/flowpath.py
srlife/thermohydraulics/thermalfluid.py
test/__init__.py
test/helpers.py
test/test_ceramic_damage_CARES.py
test/test_ceramic_damage_CARES_cyclic.py
test/test_ceramic_damage_CARES_static.py
test/test_helpers.py
test/test_material_library.py
test/test_materials.py
test/test_receiver_data.py
test/test_volume_calculation.py
test/test_writers.py
test/solvers/__init__.py
test/solvers/spring/__init__.py
test/solvers/spring/altsolver.py
test/solvers/spring/test_random_networks.py
test/solvers/spring/test_spring.py
test/solvers/thermal/__init__.py
test/solvers/thermal/run_verification.py
test/solvers/thermal/test_thermal.py
test/solvers/thermal/thermalsol.py
test/solvers/thermal/time_1d.py
test/solvers/thermal/time_2d.py
test/solvers/thermal/time_3d.py
test/solvers/tube/__init__.py
test/solvers/tube/run_structural_tube_verification.py
test/solvers/tube/test_structural_tube.py
srlife-2.0.2.dist-info/LICENSE
srlife-2.0.2.dist-info/METADATA
srlife-2.0.2.dist-info/WHEEL
srlife-2.0.2.dist-info/top_level.txt
srlife-2.0.2.dist-info/zip-safe
srlife-2.0.2.dist-info/RECORD
