Metadata-Version: 2.1
Name: srlife
Version: 2.0.2
Summary: Evaluate the structural life of a solar receiver
Home-page: https://github.com/Argonne-National-Laboratory/srlife
Author: Argonne National Laboratory
Author-email: messner@anl.gov
Keywords: materials structures modeling
Classifier: Intended Audience :: Science/Research
Classifier: License :: OSI Approved :: MIT License
Classifier: Programming Language :: Python :: 3
Classifier: Operating System :: OS Independent
Requires-Python: >=3.6
License-File: LICENSE
Requires-Dist: numpy>=1.18
Requires-Dist: scipy
Requires-Dist: h5py
Requires-Dist: nose
Requires-Dist: matplotlib
Requires-Dist: pylint
Requires-Dist: neml
Requires-Dist: scikit-fem==3.2.0
Requires-Dist: meshio
Requires-Dist: networkx
Requires-Dist: tqdm
Requires-Dist: multiprocess
Requires-Dist: dill
Requires-Dist: vtk; platform_system != "Darwin"
